{"name":"makeovermonday_2020w11-self-reported-life-satisfaction-vs-gdp-per-capita","title":"2020/W11: Self-reported Life Satisfaction vs GDP per capita","description":"---\n{\"editor\":\"simple\"}\n---\n# **Original Visualization**\n![gdp-vs-happiness.png](https://media.data.world/booMJcXbQZKHymqVU3il_gdp-vs-happiness.png)\n\n# **About this Dataset**\nSOURCE ARTICLE: [Our World in Data](https://ourworldindata.org/happiness-and-life-satisfaction)\nDATA SOURCE: [World Bank](https://datacatalog.worldbank.org/dataset/world-development-indicators)\n\n# **Objectives**\n* What works and what doesn't work with this chart? \n* How can you make it better?\n* I've added three data files. One associated with the original visualisation, one to allow you to assign countries to regions, or a .hyper file for Tableau users which joined the two sources together if you can't figure out how to do it yourselves!","homepage":"https://data.world/makeovermonday/2020w11-self-reported-life-satisfaction-vs-gdp-per-capita","resources":[{"name":"gdp_vs_happiness","schema":{"fields":[{"name":"afghanistan","title":"Afghanistan","type":"string","rdfType":"http://www.w3.org/2001/XMLSchema#string","dwSourceId":"afghanistan"},{"name":"afg","title":"AFG","type":"string","rdfType":"http://www.w3.org/2001/XMLSchema#string","dwSourceId":"afg"},{"name":"1800","title":"1800","type":"integer","rdfType":"http://www.w3.org/2001/XMLSchema#integer","dwSourceId":"1800"},{"name":"column_d","title":"Column D","type":"number","rdfType":"http://www.w3.org/2001/XMLSchema#decimal","dwSourceId":"column_d"},{"name":"column_e","title":"Column E","type":"number","rdfType":"http://www.w3.org/2001/XMLSchema#decimal","dwSourceId":"column_e"},{"name":"3280000","title":"3280000","type":"integer","rdfType":"http://www.w3.org/2001/XMLSchema#integer","dwSourceId":"3280000"}]},"path":"data/gdp_vs_happiness.csv","format":"csv"},{"name":"region_lookup","schema":{"fields":[{"name":"country","title":"Country","type":"string","rdfType":"http://www.w3.org/2001/XMLSchema#string","dwSourceId":"country"},{"name":"region","title":"Region","type":"string","rdfType":"http://www.w3.org/2001/XMLSchema#string","dwSourceId":"region"},{"name":"global_south","title":"Global South","type":"string","rdfType":"http://www.w3.org/2001/XMLSchema#string","dwSourceId":"global_south"}]},"path":"data/region_lookup.csv","format":"csv"},{"name":"original/Region LookUp.xlsx","path":"original/Region LookUp.xlsx","format":"xlsx","mediatype":"application/vnd.openxmlformats-officedocument.spreadsheetml.sheet","bytes":15342},{"name":"original/Week11.hyper","path":"original/Week11.hyper","format":"hyper","mediatype":"application/octet-stream","bytes":131072},{"name":"original/gdp-vs-happiness.csv","path":"original/gdp-vs-happiness.csv","format":"csv","mediatype":"text/csv","bytes":1488000}],"keywords":["makeover monday","happiness","gdp per capita"]}